aiotest/__init__.py
aiotest/__main__.py
aiotest/client.py
aiotest/events.py
aiotest/exception.py
aiotest/log.py
aiotest/main.py
aiotest/runners.py
aiotest/shape.py
aiotest/stats_exporter.py
aiotest/user.py
aiotest/rpc/__init__.py
aiotest/rpc/protocol.py
aiotest/rpc/zmqrpc.py
aiotest/test/__init__.py
aiotest/test/conftest.py
aiotest/test/log.py
aiotest/test/setting.py
aiotest/test/test_client.py
aiotest/test/test_main.py
aiotest/test/test_rpc.py
aiotest/test/test_runner.py
aiotest/test/test_user.py
aiotest-0.5.8.dist-info/LICENSE
aiotest-0.5.8.dist-info/METADATA
aiotest-0.5.8.dist-info/WHEEL
aiotest-0.5.8.dist-info/entry_points.txt
aiotest-0.5.8.dist-info/top_level.txt
aiotest-0.5.8.dist-info/RECORD
