Metadata-Version: 2.1
Name: aiotest
Version: 0.5.8
Summary: Developer friendly load testing framework Based on asyncio
Author-email: hewei <hewei1987@163.com>
License: MIT License
Project-URL: Homepage, https://github.com/hewei198711/aiotest
Classifier: Topic :: Software Development :: Testing :: Traffic Generation
Classifier: License :: OSI Approved :: MIT License
Classifier: Operating System :: OS Independent
Classifier: Programming Language :: Python
Classifier: Programming Language :: Python :: 3
Classifier: Programming Language :: Python :: 3.11
Classifier: Intended Audience :: Developers
Classifier: Intended Audience :: System Administrators
Classifier: Topic :: Software Development :: Testing
Classifier: Topic :: Software Development :: Testing :: Traffic Generation
Classifier: Topic :: System :: Distributed Computing
Requires-Python: >=3.11.3
License-File: LICENSE
Requires-Dist: aiohttp ==3.8.5
Requires-Dist: aiosignal ==1.3.1
Requires-Dist: async-timeout ==4.0.3
Requires-Dist: attrs ==23.1.0
Requires-Dist: charset-normalizer ==3.2.0
Requires-Dist: colorama ==0.4.6
Requires-Dist: frozenlist ==1.4.0
Requires-Dist: idna ==3.4
Requires-Dist: loguru ==0.7.1
Requires-Dist: msgpack ==1.0.5
Requires-Dist: multidict ==6.0.4
Requires-Dist: pyzmq ==25.1.1
Requires-Dist: win32-setctime ==1.1.0
Requires-Dist: yarl ==1.9.2
Requires-Dist: psutil ==5.9.5
Requires-Dist: prometheus-client ==0.17.1
Requires-Dist: tornado >=6.1
Requires-Dist: mkdocstrings[python] >=0.18
Requires-Dist: uvloop ==0.17.0 ; platform_system != "Windows"
